git_acp/__init__.py
git_acp/modules/__init__.py
git_acp/modules/git_acp.py
git_acp_ansible-1.1.2.dist-info/LICENSE
git_acp_ansible-1.1.2.dist-info/METADATA
git_acp_ansible-1.1.2.dist-info/WHEEL
git_acp_ansible-1.1.2.dist-info/top_level.txt
git_acp_ansible-1.1.2.dist-info/RECORD
