Metadata-Version: 2.1
Name: git-acp-ansible
Version: 1.1.2
Summary: Ansible module for git add/commit/push operations.
Home-page: https://github.com/lvrfrc87/git-acp-ansible
Author: Federico Olivieri
Author-email: lvrfrc87@gmail.com
License: UNKNOWN
Platform: UNKNOWN
Classifier: Topic :: Utilities
Classifier: Programming Language :: Python :: 3
Classifier: Programming Language :: Python :: 3.5
Classifier: Programming Language :: Python :: 3.6
Classifier: Programming Language :: Python :: 3.7
Classifier: Operating System :: POSIX :: Linux
Classifier: Operating System :: MacOS
Requires-Dist: ansible
